aei-1.4.0.dist-info/licenses/LICENSE.txt
pyrimaa/__init__.py
pyrimaa/aei.py
pyrimaa/analyze.py
pyrimaa/board.py
pyrimaa/game.py
pyrimaa/gameroom.py
pyrimaa/postal_controller.py
pyrimaa/roundrobin.py
pyrimaa/simple_engine.py
pyrimaa/test_runner.py
pyrimaa/util.py
pyrimaa/tests/__init__.py
pyrimaa/tests/socketadapter.py
pyrimaa/tests/test_aei.py
pyrimaa/tests/test_analyze.py
pyrimaa/tests/test_board.py
pyrimaa/tests/test_game.py
pyrimaa/tests/test_simple_engine.py
pyrimaa/tests/test_util.py
aei-1.4.0.dist-info/METADATA
aei-1.4.0.dist-info/WHEEL
aei-1.4.0.dist-info/entry_points.txt
aei-1.4.0.dist-info/top_level.txt
aei-1.4.0.dist-info/RECORD
