Metadata-Version: 2.4
Name: AEI
Version: 1.4.0
Summary: Arimaa Engine Interface tools
Author-email: Janzert <janzert@janzert.com>
License: MIT
Project-URL: Homepage, https://arimaa.janzert.com/aei
Project-URL: Source Code, https://github.com/janzert/aei
Keywords: Arimaa
Classifier: Programming Language :: Python
Classifier: Programming Language :: Python :: 3
Classifier: Programming Language :: Python :: 3.8
Classifier: Programming Language :: Python :: 3.9
Classifier: Programming Language :: Python :: 3.10
Classifier: Programming Language :: Python :: 3.11
Classifier: Programming Language :: Python :: 3.12
Classifier: Programming Language :: Python :: 3.13
Classifier: Intended Audience :: Developers
Classifier: Topic :: Games/Entertainment :: Board Games
Requires-Python: >=3.8
License-File: LICENSE.txt
Provides-Extra: dev
Requires-Dist: coverage[toml]>=7.0; extra == "dev"
Requires-Dist: ruff>=0.8.0; extra == "dev"
Requires-Dist: pre-commit>=3.0.0; extra == "dev"
Dynamic: license-file
